{
  "repo": "AugustSaintFreytag/stalker-egui-dynahud-bhs",
  "stars": 0,
  "relevance_score": 90,
  "analysis": {
    "callbacks": {
      "on_xml_read": 1,
      "on_game_load": 1,
      "ActorMenu_on_mode_changed": 1,
      "actor_on_first_update": 1,
      "actor_on_item_use": 1,
      "actor_on_net_destroy": 1,
      "actor_on_update": 1,
      "actor_on_weapon_fired": 1,
      "actor_on_weapon_zoom_in": 1,
      "actor_on_weapon_zoom_out": 1,
      "on_key_press": 1,
      "on_key_release": 1
    },
    "functions": [
      {
        "file": "gamedata\\scripts\\modxml_saint_dynahud_changes.script",
        "name": "on_xml_read",
        "params": ""
      },
      {
        "file": "gamedata\\scripts\\modxml_saint_dynahud_changes.script",
        "name": "on_ui_custom_msgs_read",
        "params": "xml_obj"
      },
      {
        "file": "gamedata\\scripts\\modxml_saint_dynahud_changes.script",
        "name": "on_dynahud_ui_read",
        "params": "xml_obj"
      },
      {
        "file": "gamedata\\scripts\\modxml_saint_dynahud_changes.script",
        "name": "on_maingame_16_read",
        "params": "xml_obj"
      },
      {
        "file": "gamedata\\scripts\\modxml_saint_dynahud_changes.script",
        "name": "on_mag_hud_read",
        "params": "xml_obj"
      },
      {
        "file": "gamedata\\scripts\\modxml_saint_dynahud_changes.script",
        "name": "on_ish_firemode_hud_read",
        "params": "xml_obj"
      },
      {
        "file": "gamedata\\scripts\\modxml_saint_dynahud_changes.script",
        "name": "on_ui_bgac_component_read",
        "params": "xml_obj"
      },
      {
        "file": "gamedata\\scripts\\modxml_saint_dynahud_changes.script",
        "name": "on_game_start",
        "params": ""
      },
      {
        "file": "gamedata\\scripts\\ui_sleep_dialog.script",
        "name": "get_immersive_sleep_hours",
        "params": "hours"
      },
      {
        "file": "gamedata\\scripts\\ui_sleep_dialog.script",
        "name": "dream_callback",
        "params": ""
      },
      {
        "file": "gamedata\\scripts\\ui_sleep_dialog.script",
        "name": "dream_callback2",
        "params": ""
      },
      {
        "file": "gamedata\\scripts\\ui_sleep_dialog.script",
        "name": "sleep",
        "params": "force"
      },
      {
        "file": "gamedata\\scripts\\ui_sleep_dialog.script",
        "name": "sleep_forced",
        "params": "hours"
      },
      {
        "file": "gamedata\\scripts\\ui_sleep_dialog.script",
        "name": "sleep_bag",
        "params": "ph_sleepbag_id, sec"
      },
      {
        "file": "gamedata\\scripts\\ui_sleep_dialog.script",
        "name": "sleep_in_zone",
        "params": "actor, npc"
      },
      {
        "file": "gamedata\\scripts\\ui_sleep_dialog.script",
        "name": "main",
        "params": ""
      },
      {
        "file": "gamedata\\scripts\\ui_sleep_dialog.script",
        "name": "on_game_start",
        "params": ""
      },
      {
        "file": "gamedata\\scripts\\zzzzzz_disable_pda_notification_icon.script",
        "name": "set_notification",
        "params": "typ, texture, tm, snd"
      },
      {
        "file": "gamedata\\scripts\\zzzz_dynahud.script",
        "name": "dynahud_on_mcm_change",
        "params": ""
      },
      {
        "file": "gamedata\\scripts\\zzzz_dynahud.script",
        "name": "initialize_plugins_support",
        "params": ""
      },
      {
        "file": "gamedata\\scripts\\zzzz_dynahud.script",
        "name": "dynahud_main_hud_controller",
        "params": ""
      },
      {
        "file": "gamedata\\scripts\\zzzz_dynahud.script",
        "name": "dynahud_bhs_hud_controller",
        "params": ""
      },
      {
        "file": "gamedata\\scripts\\zzzz_dynahud.script",
        "name": "dynahud_mag_hud_controller",
        "params": ""
      },
      {
        "file": "gamedata\\scripts\\zzzz_dynahud.script",
        "name": "get_actor_health",
        "params": ""
      },
      {
        "file": "gamedata\\scripts\\zzzz_dynahud.script",
        "name": "get_actor_power",
        "params": ""
      },
      {
        "file": "gamedata\\scripts\\zzzz_dynahud.script",
        "name": "get_actor_psy_health",
        "params": ""
      },
      {
        "file": "gamedata\\scripts\\zzzz_dynahud.script",
        "name": "get_actor_rads",
        "params": ""
      },
      {
        "file": "gamedata\\scripts\\zzzz_dynahud.script",
        "name": "is_actor_hurting_or_healing",
        "params": ""
      },
      {
        "file": "gamedata\\scripts\\zzzz_dynahud.script",
        "name": "is_actor_sprinting",
        "params": ""
      },
      {
        "file": "gamedata\\scripts\\zzzz_dynahud.script",
        "name": "actor_lowers_the_weapon",
        "params": ""
      },
      {
        "file": "gamedata\\scripts\\zzzz_dynahud.script",
        "name": "actor_raise_the_weapon",
        "params": ""
      },
      {
        "file": "gamedata\\scripts\\zzzz_dynahud.script",
        "name": "dynahud_minimap_controller",
        "params": ""
      },
      {
        "file": "gamedata\\scripts\\zzzz_dynahud.script",
        "name": "ui_show_cur_ammo",
        "params": "show"
      },
      {
        "file": "gamedata\\scripts\\zzzz_dynahud.script",
        "name": "ui_show_weapon_icon",
        "params": "show"
      },
      {
        "file": "gamedata\\scripts\\zzzz_dynahud.script",
        "name": "show_minimap",
        "params": "show"
      },
      {
        "file": "gamedata\\scripts\\zzzz_dynahud.script",
        "name": "print_tip",
        "params": "text, delay, ..."
      },
      {
        "file": "gamedata\\scripts\\zzzz_dynahud.script",
        "name": "update_shooting_tg",
        "params": ""
      },
      {
        "file": "gamedata\\scripts\\zzzz_dynahud.script",
        "name": "show_ammo_hud",
        "params": ""
      },
      {
        "file": "gamedata\\scripts\\zzzz_dynahud.script",
        "name": "hide_ammo_hud",
        "params": ""
      },
      {
        "file": "gamedata\\scripts\\zzzz_dynahud.script",
        "name": "exit_weapon_aiming",
        "params": ""
      },
      {
        "file": "gamedata\\scripts\\zzzz_dynahud.script",
        "name": "weapon_hud_update",
        "params": "action"
      },
      {
        "file": "gamedata\\scripts\\zzzz_dynahud.script",
        "name": "dynahud_weapon_hud_controller",
        "params": ""
      },
      {
        "file": "gamedata\\scripts\\zzzz_dynahud.script",
        "name": "show_firemode_gui",
        "params": "show"
      },
      {
        "file": "gamedata\\scripts\\zzzz_dynahud.script",
        "name": "check_all_mainhud_bars_are_hidden",
        "params": ""
      },
      {
        "file": "gamedata\\scripts\\zzzz_dynahud.script",
        "name": "check_all_mainhud_bars_are_static_and_above_threshold",
        "params": ""
      },
      {
        "file": "gamedata\\scripts\\zzzz_dynahud.script",
        "name": "dynahud_autohide_main_hud",
        "params": ""
      },
      {
        "file": "gamedata\\scripts\\zzzz_dynahud.script",
        "name": "dynahud_main_hud_update",
        "params": ""
      },
      {
        "file": "gamedata\\scripts\\zzzz_dynahud.script",
        "name": "main_hud_bg_controller",
        "params": ""
      },
      {
        "file": "gamedata\\scripts\\zzzz_dynahud.script",
        "name": "hide_mainhud_bg_with_delay",
        "params": ""
      },
      {
        "file": "gamedata\\scripts\\zzzz_dynahud.script",
        "name": "hide_mainhud_bg",
        "params": ""
      },
      {
        "file": "gamedata\\scripts\\zzzz_dynahud.script",
        "name": "show_main_hud_bg",
        "params": ""
      },
      {
        "file": "gamedata\\scripts\\zzzz_dynahud.script",
        "name": "set_main_hud_bg_visibility",
        "params": "show"
      },
      {
        "file": "gamedata\\scripts\\zzzz_dynahud.script",
        "name": "autoshow_main_hud_bg",
        "params": ""
      },
      {
        "file": "gamedata\\scripts\\zzzz_dynahud.script",
        "name": "status_icons_controller",
        "params": ""
      },
      {
        "file": "gamedata\\scripts\\zzzz_dynahud.script",
        "name": "show_status_icons",
        "params": ""
      },
      {
        "file": "gamedata\\scripts\\zzzz_dynahud.script",
        "name": "dynamic_cold_system_init",
        "params": ""
      },
      {
        "file": "gamedata\\scripts\\zzzz_dynahud.script",
        "name": "cold_system_update",
        "params": ""
      },
      {
        "file": "gamedata\\scripts\\zzzz_dynahud.script",
        "name": "cold_system_controller",
        "params": ""
      },
      {
        "file": "gamedata\\scripts\\zzzz_dynahud.script",
        "name": "enable_bhs_hud",
        "params": ""
      },
      {
        "file": "gamedata\\scripts\\zzzz_dynahud.script",
        "name": "disable_bhs_hud",
        "params": ""
      },
      {
        "file": "gamedata\\scripts\\zzzz_dynahud.script",
        "name": "dynahud_bhs_hud_switcher",
        "params": ""
      },
      {
        "file": "gamedata\\scripts\\zzzz_dynahud.script",
        "name": "check_limbs_fully_healed",
        "params": ""
      },
      {
        "file": "gamedata\\scripts\\zzzz_dynahud.script",
        "name": "dynahud_bhs_hud_dismiss_update",
        "params": ""
      },
      {
        "file": "gamedata\\scripts\\zzzz_dynahud.script",
        "name": "dynahud_dynamic_bhs_hud_update",
        "params": ""
      },
      {
        "file": "gamedata\\scripts\\zzzz_dynahud.script",
        "name": "create_dismiss_bhs_event",
        "params": ""
      },
      {
        "file": "gamedata\\scripts\\zzzz_dynahud.script",
        "name": "dynahud_mags_ui_update",
        "params": "action"
      },
      {
        "file": "gamedata\\scripts\\zzzz_dynahud.script",
        "name": "dynahud_mags_ui_update_ammocheck",
        "params": ""
      },
      {
        "file": "gamedata\\scripts\\zzzz_dynahud.script",
        "name": "preview_companion_hud_event",
        "params": ""
      },
      {
        "file": "gamedata\\scripts\\zzzz_dynahud.script",
        "name": "companion_hud_on_key_press",
        "params": ""
      },
      {
        "file": "gamedata\\scripts\\zzzz_dynahud.script",
        "name": "companion_hud_on_key_release",
        "params": "dik"
      },
      {
        "file": "gamedata\\scripts\\zzzz_dynahud.script",
        "name": "is_companions_squad_in_danger",
        "params": ""
      },
      {
        "file": "gamedata\\scripts\\zzzz_dynahud.script",
        "name": "init_companion_hud",
        "params": ""
      },
      {
        "file": "gamedata\\scripts\\zzzz_dynahud.script",
        "name": "update_companion_hud",
        "params": ""
      },
      {
        "file": "gamedata\\scripts\\zzzz_dynahud.script",
        "name": "on_game_start",
        "params": ""
      },
      {
        "file": "gamedata\\scripts\\z_alticons.script",
        "name": "main_hud_bg_off_status_icons",
        "params": ""
      },
      {
        "file": "gamedata\\scripts\\z_alticons.script",
        "name": "main_hud_bg_on_status_icons",
        "params": ""
      },
      {
        "file": "gamedata\\scripts\\z_alticons.script",
        "name": "loadUIStatic",
        "params": ""
      },
      {
        "file": "gamedata\\scripts\\z_alticons.script",
        "name": "dynahud_on_mcm_change",
        "params": ""
      },
      {
        "file": "gamedata\\scripts\\z_alticons.script",
        "name": "load_mcm_settings",
        "params": ""
      },
      {
        "file": "gamedata\\scripts\\z_alticons.script",
        "name": "on_game_start",
        "params": ""
      },
      {
        "file": "gamedata\\scripts\\z_saint_disable_surge_psi_indicator.script",
        "name": "surge_manager.CSurgeManager.displayIndicators",
        "params": "power"
      }
    ],
    "api_calls": {
      "ui_options.get": 11,
      "game.translate_string": 10,
      "ui_mcm.set": 7,
      "level.add_cam_effector": 5,
      "axr_companions.activate_hud": 5,
      "db.actor.active_item": 4,
      "ui_sleep_dialog.UISleep": 3,
      "game.actor_weapon_lowered": 3,
      "level.add_pp_effector": 2,
      "db.actor.give_info_portion": 2,
      "ui_options.set": 2,
      "ui_bartgac_mcm.BGAC_ON": 2,
      "ui_bartgac_mcm.BGAC_OFF": 2,
      "axr_companions.on_key_release": 2,
      "axr_companions.deactivate_hud": 2,
      "level.get_time_hours": 1,
      "db.actor.position": 1,
      "db.actor.activate_slot": 1,
      "db.actor.object": 1,
      "level.change_game_time": 1,
      "ui_debug_launcher.inject": 1,
      "level.object_by_id": 1,
      "db.actor.active_slot": 1,
      "db.actor.active_detector": 1,
      "db.actor.id": 1
    },
    "ini_read_types": [],
    "script_files": [
      "gamedata\\scripts\\modxml_saint_dynahud_changes.script",
      "gamedata\\scripts\\ui_sleep_dialog.script",
      "gamedata\\scripts\\z_alticons.script",
      "gamedata\\scripts\\z_saint_disable_surge_psi_indicator.script",
      "gamedata\\scripts\\zzzz_dynahud.script",
      "gamedata\\scripts\\zzzzzz_disable_pda_notification_icon.script"
    ],
    "config_files": [
      "gamedata\\configs\\ui\\textures_descr\\dynahud.xml",
      "gamedata\\configs\\ui\\ui_custom_msgs.xml"
    ],
    "file_count": 6
  }
}